jmt
