Metadata-Version: 1.0
Name: jmt
Version: 0.0.0.21
Summary: custom functions to enhance popular python modules
Home-page: UNKNOWN
Author: Jared Ticotin
Author-email: UNKNOWN
License: UNKNOWN
Platform: UNKNOWN
